ip2vulns/__init__.py
ip2vulns/ip2vulns.py
ip2vulns/version.py
ip2vulns/Module/CVE.py
ip2vulns/Module/InternetDB.py
ip2vulns/Module/__init__.py
ip2vulns/Services/CveService.py
ip2vulns/Services/InternetDBService.py
ip2vulns/Services/__init__.py
ip2vulns/Utils/ArgUtils.py
ip2vulns/Utils/DatetimeUtils.py
ip2vulns/Utils/IpUtils.py
ip2vulns/Utils/ListUtils.py
ip2vulns/Utils/LogUtils.py
ip2vulns/Utils/OutputUtils.py
ip2vulns/Utils/PathUtils.py
ip2vulns/Utils/PipeUtils.py
ip2vulns/Utils/QueryUtils.py
ip2vulns/Utils/__init__.py
ip2vulns-1.1.0.dist-info/licenses/LICENSE
ip2vulns-1.1.0.dist-info/METADATA
ip2vulns-1.1.0.dist-info/WHEEL
ip2vulns-1.1.0.dist-info/entry_points.txt
ip2vulns-1.1.0.dist-info/top_level.txt
ip2vulns-1.1.0.dist-info/RECORD
