Metadata-Version: 2.4
Name: ip2vulns
Version: 1.1.0
Summary: An IP to vulnerability utility
Home-page: https://github.com/BoxHezi/ip2vulns
Author: Box Hezi
Author-email: hezipypi.yixdpu@bumpmail.io
Requires-Python: >=3.8
License-File: LICENSE
Requires-Dist: requests
Requires-Dist: tqdm
Dynamic: author
Dynamic: author-email
Dynamic: description
Dynamic: description-content-type
Dynamic: home-page
Dynamic: license-file
Dynamic: requires-dist
Dynamic: requires-python
Dynamic: summary
